cat_picture-0.2.1.dist-info/METADATA
cat_picture-0.2.1.dist-info/WHEEL
cat_picture/.pytest_cache/.gitignore
cat_picture/.pytest_cache/CACHEDIR.TAG
cat_picture/.pytest_cache/README.md
cat_picture/.pytest_cache/v/cache/nodeids
cat_picture/.pytest_cache/v/cache/stepwise
cat_picture/__init__.py
cat_picture/cat.py
cat_picture-0.2.1.dist-info/RECORD
