Metadata-Version: 2.1
Name: cat-picture
Version: 0.2.1
Summary: I will show you a picture of a cat.
Author-Email: gogododo <4dovidovi4@gmail.com>
License: MIT
Requires-Python: >=3.7
